flattaxdb/__init__.py
flattaxdb/db.py
flattaxdb-0.1.0.dist-info/LICENSE
flattaxdb-0.1.0.dist-info/METADATA
flattaxdb-0.1.0.dist-info/WHEEL
flattaxdb-0.1.0.dist-info/top_level.txt
flattaxdb-0.1.0.dist-info/RECORD
