Metadata-Version: 2.1
Name: flattaxdb
Version: 0.1.0
Summary: Yet another Python library to work with taxonomy databases
Author-email: Brandon Seah <brandon.seah@thuenen.de>
License: 
Keywords: taxonomy,NCBI,GBIF
Requires-Python: >=3.9
License-File: LICENSE
